{
  "capability": "amgmcp_query_resource_graph",
  "parameters": {
    "subscription_ids": [
      "22222222-2222-2222-2222-222222222222"
    ],
    "query": "Resources | where resourceGroup =~ 'rg-locked-prod' | project id, name, type, location, sku, tags"
  },
  "parameters_digest": "2499d700b860b49b2160d03f6c9ceb1459338bd467cddcf132901f08454ebfcd",
  "response": {
    "content": {
      "data": [
        {
          "id": "/subscriptions/22222222-2222-2222-2222-222222222222/resourceGroups/rg-locked-prod/providers/Microsoft.Compute/virtualMachines/vm-prod-1",
          "name": "vm-prod-1",
          "type": "Microsoft.Compute/virtualMachines",
          "location": "westus2",
          "sku": {
            "name": "Standard_D8s_v5"
          },
          "tags": {
            "owner": "platform-team",
            "env": "prod"
          }
        }
      ],
      "count": 1
    },
    "isError": false
  }
}
